MANIFEST.in
README.md
setup.cfg
setup.py
cabot_alert_dingding/__init__.py
cabot_alert_dingding/models.py
cabot_alert_dingding.egg-info/PKG-INFO
cabot_alert_dingding.egg-info/SOURCES.txt
cabot_alert_dingding.egg-info/dependency_links.txt
cabot_alert_dingding.egg-info/top_level.txt
cabot_alert_dingding/migrations/0001_initial.py
cabot_alert_dingding/migrations/__init__.py