Metadata-Version: 2.1
Name: cabot-alert-dingding
Version: 0.2.1
Summary: A Dingding plugin for Cabot
Home-page: https://github.com/hanya070603
Author: hanya
Author-email: 464975798@qq.com
License: UNKNOWN
Download-URL: https://github.com/hanya070603/
Keywords: cabot,dingding,status check
Platform: UNKNOWN
